{
  "updated": "2026/05/20 22:25 台北時間",
  "bullets": [
    "🇺🇸🇮🇷 川普暫緩對伊朗軍事打擊 「正進行嚴肅談判」",
    "🇺🇸🇨🇺 魯比歐制裁11名古巴官員 含司法能源部長及軍參謀長",
    "🇷🇺🇨🇳 普京啟程訪中 19-20日北京國事訪問會晤習近平",
    "🇺🇦🇷🇺 莫斯科遭1年來最大規模空襲 俄多地至少4死",
    "🇮🇱🇮🇷 以軍空襲伊朗Shahran油庫 整座設施陷火海",
    "🇺🇸🇨🇳 川習會北京登場 伊朗/台灣/AI/貿易五大火線攤牌"
  ],
  "categories": [
    {
      "icon": "⚔️",
      "title": "中東戰事",
      "items": [
        {
          "icon": "🇺🇸",
          "title": "川普暫緩對伊朗軍事打擊",
          "desc": "川普 5/19 宣布暫緩原訂週二對伊朗的軍事打擊，因「正在進行嚴肅談判」。他同時指示美軍「隨時準備對伊朗發動全面、大規模攻擊，若未達成可接受的協議」。同日美參議院推進終結伊朗戰爭法案，Cassidy 於初選失利後倒戈支持。"
        },
        {
          "icon": "🇮🇱",
          "title": "以軍空襲伊朗 Shahran 油庫",
          "desc": "以色列空襲擊中德黑蘭 Shahran 油庫，整座設施陷入火海。同時以色列當局加速對東耶路撒冷巴勒斯坦人發布拆遷令，人權組織與聯合國專家對此表達關切。"
        }
      ]
    },
    {
      "icon": "🤝",
      "title": "美中峰會",
      "items": [
        {
          "icon": "🇨🇳",
          "title": "川習會北京登場 五大火線議題",
          "desc": "川普與習近平於北京舉行峰會。議題：伊朗（川普盼中方向伊朗施壓恢復荷莫茲海峽航運）、台灣（川普表態擬與中方討論對台軍售，北京盼美方將「不支持台獨」改為「反對台獨」）、AI、貿易爭端。為自 2017 年以來首位美國總統訪中。"
        }
      ]
    },
    {
      "icon": "🌍",
      "title": "俄烏戰場",
      "items": [
        {
          "icon": "🇺🇦",
          "title": "莫斯科遭烏克蘭最大規模空襲",
          "desc": "俄羅斯多地遭烏克蘭無人機大舉攻擊，造成至少 4 人死亡，其中首都莫斯科遭遇 1 年多來最大規模空襲。同時俄羅斯空襲基輔公寓造成至少 24 人死亡，烏克蘭亦反擊里亞贊（Ryazan）住宅區與煉油廠。"
        },
        {
          "icon": "🇷🇺",
          "title": "普京啟程訪中 5/19-20",
          "desc": "應習近平邀請，俄羅斯總統普京 5/19-20 對中國進行國事訪問。出訪前夕，一架俄羅斯無人機夜間於黑海擊中一艘中資貨輪，俄方亦公開表達對中俄關係的不滿。"
        }
      ]
    },
    {
      "icon": "🚫",
      "title": "新一輪制裁",
      "items": [
        {
          "icon": "🇨🇺",
          "title": "美制裁11名古巴政府高官",
          "desc": "國務卿魯比歐 5/19 宣布制裁 11 名古巴政府官員，包含司法部長、能源礦業部長、通信部長、古巴軍隊參謀長與軍事反情報參謀長。制裁凍結其在美國金融體系內接觸的任何資產（多數受制裁者先前已被列入美方名單）。"
        }
      ]
    },
    {
      "icon": "🇪🇺",
      "title": "美歐裂痕",
      "items": [
        {
          "icon": "🇵🇱",
          "title": "美國取消向波蘭部署4000美軍",
          "desc": "五角大廈取消原訂向波蘭部署 4,000 名美軍的計畫，白宮對 NATO 未參與伊朗戰爭表達不滿。延續川普政府以削減駐歐美軍、提高歐盟輸美汽車關稅作為跨大西洋關係籌碼的態勢。"
        }
      ]
    }
  ]
}